packed_struct/__init__.py
packed_struct/types.py
tests/__init__.py
tests/test_utils.py
tests/tests.py
py_packed_struct-0.6.dist-info/LICENSE
py_packed_struct-0.6.dist-info/METADATA
py_packed_struct-0.6.dist-info/WHEEL
py_packed_struct-0.6.dist-info/top_level.txt
py_packed_struct-0.6.dist-info/RECORD
