Metadata-Version: 2.1
Name: py-packed-struct
Version: 0.6
Summary: An implementation of C-like packed structures in Python
Home-page: https://github.com/lu-maca/py-packed-struct
Author: Luca Macavero
Author-email: luca.macavero@gmail.com
Maintainer: Luca Macavero
Maintainer-email: luca.macavero@gmail.com
Requires-Python: >=3.5
License-File: LICENSE
Requires-Dist: bitstruct
